extend_zarr/__init__.py
extend_zarr/_version.py
extend_zarr/utils.py
extend_zarr-0.1.2.dist-info/METADATA
extend_zarr-0.1.2.dist-info/WHEEL
extend_zarr-0.1.2.dist-info/top_level.txt
extend_zarr-0.1.2.dist-info/RECORD
