Metadata-Version: 2.4
Name: extend-zarr
Version: 0.1.2
Author-email: Taka <takahisa.amano@eodc.eu>
Project-URL: Homepage, https://github.com/eodcgmbh/extend-zarr/
Project-URL: Repository, https://github.com/eodcgmbh/extend-zarr.git
Project-URL: Issues, https://github.com/eodcgmbh/extend-zarr/issues
Requires-Python: <3.13,>=3.11
Requires-Dist: dask<2026
Requires-Dist: numpy<3
Requires-Dist: xarray<2026
Requires-Dist: zarr<4
